fslock/__init__.py
fslock/cache.py
fslock/unix.py
fslock-2.1.1.dist-info/LICENSE.txt
fslock-2.1.1.dist-info/METADATA
fslock-2.1.1.dist-info/WHEEL
fslock-2.1.1.dist-info/top_level.txt
fslock-2.1.1.dist-info/RECORD
