Metadata-Version: 2.1
Name: fslock
Version: 2.1.1
Summary: Shared and exclusive file locking using flock(2)
Home-page: https://github.com/remram44/python-fslock
Author: Remi Rampin
Author-email: remi@rampin.org
Maintainer: Remi Rampin
Maintainer-email: remi@rampin.org
License: MIT
Project-URL: Source, https://github.com/remram44/python-fslock
Project-URL: Tracker, https://github.com/remram44/python-fslock/issues
Keywords: lock,flock,file lock,locking,filesystem
Platform: UNKNOWN
Classifier: Development Status :: 5 - Production/Stable
Classifier: Intended Audience :: Developers
Classifier: License :: OSI Approved :: MIT License
Classifier: Operating System :: POSIX
Classifier: Programming Language :: Python :: 3 :: Only
License-File: LICENSE.txt
